kathara.py
Kathara/__init__.py
Kathara/decorators.py
Kathara/exceptions.py
Kathara/strings.py
Kathara/types.py
Kathara/utils.py
Kathara/version.py
Kathara/auth/PrivilegeHandler.py
Kathara/auth/__init__.py
Kathara/cli/__init__.py
Kathara/cli/command/CheckCommand.py
Kathara/cli/command/ConnectCommand.py
Kathara/cli/command/ExecCommand.py
Kathara/cli/command/LcleanCommand.py
Kathara/cli/command/LconfigCommand.py
Kathara/cli/command/LinfoCommand.py
Kathara/cli/command/ListCommand.py
Kathara/cli/command/LrestartCommand.py
Kathara/cli/command/LstartCommand.py
Kathara/cli/command/SettingsCommand.py
Kathara/cli/command/VcleanCommand.py
Kathara/cli/command/VconfigCommand.py
Kathara/cli/command/VstartCommand.py
Kathara/cli/command/WipeCommand.py
Kathara/cli/command/__init__.py
Kathara/cli/ui/__init__.py
Kathara/cli/ui/utils.py
Kathara/cli/ui/event/HandleDockerImagePull.py
Kathara/cli/ui/event/HandleMachineTerminal.py
Kathara/cli/ui/event/HandleProgressBar.py
Kathara/cli/ui/event/UpdateDockerImage.py
Kathara/cli/ui/event/__init__.py
Kathara/cli/ui/event/register.py
Kathara/cli/ui/setting/CommonOptionsHandler.py
Kathara/cli/ui/setting/DockerOptionsHandler.py
Kathara/cli/ui/setting/KubernetesOptionsHandler.py
Kathara/cli/ui/setting/SettingsMenuFactory.py
Kathara/cli/ui/setting/__init__.py
Kathara/cli/ui/setting/utils.py
Kathara/event/EventDispatcher.py
Kathara/event/__init__.py
Kathara/foundation/__init__.py
Kathara/foundation/cli/CliArgs.py
Kathara/foundation/cli/__init__.py
Kathara/foundation/cli/command/Command.py
Kathara/foundation/cli/command/CommandFactory.py
Kathara/foundation/cli/command/__init__.py
Kathara/foundation/cli/ui/__init__.py
Kathara/foundation/cli/ui/setting/OptionsHandler.py
Kathara/foundation/cli/ui/setting/OptionsHandlerFactory.py
Kathara/foundation/cli/ui/setting/__init__.py
Kathara/foundation/factory/Factory.py
Kathara/foundation/factory/__init__.py
Kathara/foundation/manager/IManager.py
Kathara/foundation/manager/ManagerFactory.py
kathara-3.8.0.dist-info/licenses/LICENSE
kathara-3.8.0.dist-info/METADATA
kathara-3.8.0.dist-info/WHEEL
kathara-3.8.0.dist-info/top_level.txt
kathara-3.8.0.dist-info/RECORD
