Metadata-Version: 2.4
Name: kathara
Version: 3.8.0
Summary: A lightweight container-based network emulation tool.
Home-page: https://www.kathara.org
Download-URL: https://github.com/KatharaFramework/Kathara/archive/refs/tags/3.8.0.tar.gz
Author: Kathara Framework
Author-email: Kathara Framework <contact@kathara.org>
Maintainer-email: Tommaso Caiazzi <contact@kathara.org>, Mariano Scazzariello <contact@kathara.org>, Lorenzo Ariemma <contact@kathara.org>
License-Expression: GPL-3.0
Project-URL: Homepage, https://www.kathara.org
Project-URL: Bug Reports, https://github.com/KatharaFramework/Kathara/issues
Project-URL: Source, https://github.com/KatharaFramework/Kathara
Keywords: NETWORK-EMULATION,CONTAINERS,NFV
Classifier: Development Status :: 5 - Production/Stable
Classifier: Intended Audience :: Science/Research
Classifier: Intended Audience :: Education
Classifier: Intended Audience :: Telecommunications Industry
Classifier: Topic :: Software Development :: Build Tools
Classifier: Programming Language :: Python :: 3.9
Classifier: Programming Language :: Python :: 3.10
Classifier: Programming Language :: Python :: 3.11
Requires-Python: >=3.9
License-File: LICENSE
Requires-Dist: binaryornot>=0.4.4
Requires-Dist: docker>=7.0.0
Requires-Dist: kubernetes>=23.3.0
Requires-Dist: requests>=2.22.0
Requires-Dist: slug>=2.0
Requires-Dist: pyroute2
Requires-Dist: rich
Requires-Dist: fs>=2.4.16
Requires-Dist: chardet
Requires-Dist: libtmux>=0.8.2; platform_system == "darwin" or platform_system == "linux"
Requires-Dist: appscript>=1.1.0; platform_system == "darwin"
Requires-Dist: pypiwin32>=223; platform_system == "win32"
Requires-Dist: windows-curses>=2.1.0; platform_system == "win32"
Provides-Extra: test
Requires-Dist: pytest; extra == "test"
Dynamic: author
Dynamic: download-url
Dynamic: home-page
Dynamic: license-file
